reseval/__init__.py
reseval/__main__.py
reseval/constants.py
reseval/core.py
reseval/error.py
reseval/filter.py
reseval/load.py
reseval/npm.py
reseval/plot.py
reseval/random.py
reseval/stats.py
reseval/app/__init__.py
reseval/app/heroku.py
reseval/assets/Procfile
reseval/assets/package-lock.json
reseval/assets/package.json
reseval/assets/server.ts
reseval/assets/survey.xml
reseval/assets/tsconfig.json
reseval/assets/client/package-lock.json
reseval/assets/client/package.json
reseval/assets/client/static.json
reseval/assets/client/public/favicon.ico
reseval/assets/client/public/index.html
reseval/assets/client/public/manifest.json
reseval/assets/client/public/robots.txt
reseval/assets/client/src/App.js
reseval/assets/client/src/Survey.js
reseval/assets/client/src/index.js
reseval/assets/client/src/components/Audio.js
reseval/assets/client/src/components/Button.js
reseval/assets/client/src/components/Image.js
reseval/assets/client/src/components/Markdown.js
reseval/assets/client/src/components/Media.js
reseval/assets/client/src/components/MediaRadioButtonGroup.js
reseval/assets/client/src/components/MediaSliderGroup.js
reseval/assets/client/src/components/RadioButtonGroup.js
reseval/assets/client/src/components/Text.js
reseval/assets/client/src/components/Video.js
reseval/assets/client/src/components/WordSelection.js
reseval/assets/client/src/css/components.css
reseval/assets/client/src/css/index.css
reseval/assets/client/src/json/.gitkeep
reseval/assets/client/src/pages/EndPage.js
reseval/assets/client/src/pages/FeedbackPage.js
reseval/assets/client/src/pages/QualificationPage.js
reseval/assets/client/src/pages/TaskPage.js
reseval/assets/client/src/pages/WelcomePage.js
reseval/assets/client/src/questions/FreeResponse.js
reseval/assets/client/src/questions/ListeningTest.js
reseval/assets/client/src/questions/MultipleChoice.js
reseval/assets/client/src/questions/Question.js
reseval/assets/client/src/test/AB.js
reseval/assets/client/src/test/ABX.js
reseval-0.1.6.dist-info/LICENSE
reseval-0.1.6.dist-info/METADATA
reseval-0.1.6.dist-info/WHEEL
reseval-0.1.6.dist-info/top_level.txt
reseval-0.1.6.dist-info/RECORD
