Metadata-Version: 2.1
Name: reseval
Version: 0.1.6
Summary: Reproducible Subjective Evaluation
Home-page: https://github.com/reseval/reseval
Author: Max Morrison, Brian Tang, Gefei Tan, Bryan Pardo
Author-email: maxrmorrison@gmail.com
Keywords: annotation,audio,ab,abx,crowdsourcing,evaluation,image,mos,mushra,speech,subjective
License-File: LICENSE
Requires-Dist: appdirs >=1.4.4
Requires-Dist: boto3 >=1.21.3
Requires-Dist: matplotlib >=3.5.2
Requires-Dist: mysql-connector-python >=8.0.28
Requires-Dist: psutil >=5.9.0
Requires-Dist: python-dotenv >=0.19.2
Requires-Dist: pyyaml >=6.0
Requires-Dist: rich >=11.2.0
Requires-Dist: scipy >=1.8.0
Requires-Dist: xmltodict >=0.12.0
Requires-Dist: heroku3 >=5.1.4
